ps-minifier/__init__.py
ps-minifier/psminifier.py
ps_minifier/__init__.py
ps_minifier/psminifier.py
ps_minifier-0.2.0.dist-info/LICENSE
ps_minifier-0.2.0.dist-info/METADATA
ps_minifier-0.2.0.dist-info/WHEEL
ps_minifier-0.2.0.dist-info/entry_points.txt
ps_minifier-0.2.0.dist-info/top_level.txt
ps_minifier-0.2.0.dist-info/RECORD
