Metadata-Version: 2.1
Name: ps-minifier
Version: 0.2.0
Summary: A minifier for PowerShell scripts.
Home-page: https://github.com/Willumz/ps-minifier
Author: Willumz
License: UNKNOWN
Platform: UNKNOWN
Classifier: Programming Language :: Python :: 3
Classifier: License :: OSI Approved :: MIT License
